shapeout2/__init__.py
shapeout2/__main__.py
shapeout2/_version.py
shapeout2/extensions.py
shapeout2/idiom.py
shapeout2/meta_tool.py
shapeout2/plot_cache.py
shapeout2/session.py
shapeout2/util.py
shapeout2/gui/__init__.py
shapeout2/gui/main.py
shapeout2/gui/main.ui
shapeout2/gui/pipeline_plot.py
shapeout2/gui/pipeline_plot.ui
shapeout2/gui/preferences.py
shapeout2/gui/preferences.ui
shapeout2/gui/update.py
shapeout2/gui/analysis/__init__.py
shapeout2/gui/analysis/ana_basins.py
shapeout2/gui/analysis/ana_basins.ui
shapeout2/gui/analysis/ana_filter.py
shapeout2/gui/analysis/ana_filter.ui
shapeout2/gui/analysis/ana_log.py
shapeout2/gui/analysis/ana_log.ui
shapeout2/gui/analysis/ana_meta.py
shapeout2/gui/analysis/ana_meta.ui
shapeout2/gui/analysis/ana_plot.py
shapeout2/gui/analysis/ana_plot.ui
shapeout2/gui/analysis/ana_slot.py
shapeout2/gui/analysis/ana_slot.ui
shapeout2/gui/analysis/ana_tables.py
shapeout2/gui/analysis/ana_tables.ui
shapeout2/gui/analysis/ana_view.py
shapeout2/gui/analysis/ana_view.ui
shapeout2/gui/analysis/dlg_slot_reorder.py
shapeout2/gui/analysis/dlg_slot_reorder.ui
shapeout2/gui/bulk/__init__.py
shapeout2/gui/bulk/bulk_emodulus.py
shapeout2/gui/bulk/bulk_emodulus.ui
shapeout2/gui/compute/__init__.py
shapeout2/gui/compute/comp_lme4.py
shapeout2/gui/compute/comp_lme4.ui
shapeout2/gui/compute/comp_lme4_dataset.py
shapeout2/gui/compute/comp_lme4_dataset.ui
shapeout2/gui/compute/comp_lme4_results.py
shapeout2/gui/compute/comp_lme4_results.ui
shapeout2/gui/compute/comp_stats.py
shapeout2/gui/compute/comp_stats.ui
shapeout2/gui/dcor/__init__.py
shapeout2/gui/dcor/dcor.ui
shapeout2/gui/export/__init__.py
shapeout2/gui/export/e2data.py
shapeout2/gui/export/e2data.ui
shapeout2/gui/export/e2filter.py
shapeout2/gui/export/e2filter.ui
shapeout2/gui/export/e2plot.py
shapeout2/gui/export/e2plot.ui
shapeout2/gui/matrix/__init__.py
shapeout2/gui/matrix/block_matrix.py
shapeout2/gui/matrix/block_matrix.ui
shapeout2/gui/matrix/data_matrix.py
shapeout2-2.22.1.dist-info/licenses/LICENSE
shapeout2-2.22.1.dist-info/METADATA
shapeout2-2.22.1.dist-info/WHEEL
shapeout2-2.22.1.dist-info/entry_points.txt
shapeout2-2.22.1.dist-info/top_level.txt
shapeout2-2.22.1.dist-info/RECORD
